score/es/__init__.py
score/es/pyramid.py
score.es-0.1.7.dist-info/DESCRIPTION.rst
score.es-0.1.7.dist-info/METADATA
score.es-0.1.7.dist-info/RECORD
score.es-0.1.7.dist-info/WHEEL
score.es-0.1.7.dist-info/metadata.json
score.es-0.1.7.dist-info/top_level.txt
